Metadata-Version: 1.1
Name: fdriver
Version: 0.0.9
Summary: mvc archhitecture for fastapi
Home-page: https://github.com/AdamMusa/fdriver
Author: AdamMusa
Author-email: adammusa2222@gmail.com
License: MIT
Keywords: fdriver,fastapi mvc,mvc for fastapi,goode architecture for fastapi
Platform: UNKNOWN
Classifier: License :: OSI Approved :: MIT License
Classifier: Programming Language :: Python :: 3.7
